sqlython/__init__.py
sqlython/builder.py
sqlython/connection.py
sqlython/filter.py
sqlython/model.py
sqlython-1.3.1.dist-info/LICENSE
sqlython-1.3.1.dist-info/METADATA
sqlython-1.3.1.dist-info/WHEEL
sqlython-1.3.1.dist-info/top_level.txt
sqlython-1.3.1.dist-info/RECORD
