Metadata-Version: 2.2
Name: sqlython
Version: 1.3.1
Summary: A lightweight and user-friendly SQL query builder for Python
Home-page: https://github.com/uziins/sqlython
Author: Fauzi NS
Author-email: fauzi.ns@icloud.com
Classifier: Programming Language :: Python :: 3
Classifier: License :: OSI Approved :: MIT License
Classifier: Operating System :: OS Independent
Requires-Python: >=3.6
License-File: LICENSE
Requires-Dist: python-dotenv
Requires-Dist: mysql-connector-python
Dynamic: author
Dynamic: author-email
Dynamic: classifier
Dynamic: description
Dynamic: description-content-type
Dynamic: home-page
Dynamic: requires-dist
Dynamic: requires-python
Dynamic: summary
